mockpac/__init__.py
mockpac/main.py
mocpac-0.1.dist-info/METADATA
mocpac-0.1.dist-info/WHEEL
mocpac-0.1.dist-info/top_level.txt
mocpac-0.1.dist-info/RECORD
