Metadata-Version: 2.1
Name: mocpac
Version: 0.1
Requires-Dist: pandas
